myimpy/__init__.py
myimpy/basic.py
myimpy/morphology.py
myimpy/text.py
myimpy/transformation.py
myimpy-1.6.dist-info/METADATA
myimpy-1.6.dist-info/WHEEL
myimpy-1.6.dist-info/top_level.txt
myimpy-1.6.dist-info/RECORD
