Metadata-Version: 2.1
Name: myimpy
Version: 1.6
Summary: Imaging processing methods
Home-page: https://github.com/JinhangZhu/myimpy
Author: Jinhang Zhu
Author-email: jinhang.d.zhu@gmail.com
License: MIT
Platform: UNKNOWN
